chytorch/zoo/rxnmap/__init__.py
chytorch/zoo/rxnmap/weights.pt
chytorch_rxnmap-1.4.dist-info/LICENSE
chytorch_rxnmap-1.4.dist-info/METADATA
chytorch_rxnmap-1.4.dist-info/WHEEL
chytorch_rxnmap-1.4.dist-info/top_level.txt
chytorch_rxnmap-1.4.dist-info/RECORD
